epub_pipeline/__init__.py
epub_pipeline/cli.py
epub_pipeline/config.py
epub_pipeline/models.py
epub_pipeline/pipeline/cover_manager.py
epub_pipeline/pipeline/drive_uploader.py
epub_pipeline/pipeline/epub_manager.py
epub_pipeline/pipeline/kepub_handler.py
epub_pipeline/pipeline/orchestrator.py
epub_pipeline/search/book_finder.py
epub_pipeline/search/confidence.py
epub_pipeline/search/provider.py
epub_pipeline/search/providers/google.py
epub_pipeline/search/providers/openlibrary.py
epub_pipeline/utils/formatter.py
epub_pipeline/utils/isbn_utils.py
epub_pipeline/utils/logger.py
epub_pipeline/utils/text_utils.py
epub_pipeline-1.0.1.dist-info/licenses/LICENSE
tests/test_book_finder_logic.py
tests/test_cli.py
tests/test_confidence.py
tests/test_epub_manager_save.py
tests/test_epub_manager_update.py
tests/test_openlibrary.py
tests/test_orchestrator.py
tests/test_pipeline.py
tests/test_pipeline_components.py
tests/test_providers.py
tests/test_utils.py
tests/test_utils_extended.py
tools/dry_run.py
tools/inspect.py
tools/search.py
tools/upload.py
epub_pipeline-1.0.1.dist-info/METADATA
epub_pipeline-1.0.1.dist-info/WHEEL
epub_pipeline-1.0.1.dist-info/entry_points.txt
epub_pipeline-1.0.1.dist-info/top_level.txt
epub_pipeline-1.0.1.dist-info/RECORD
