Metadata-Version: 2.4
Name: epub-pipeline
Version: 1.0.1
Summary: Automated pipeline for Ebook metadata enrichment, conversion, and cloud upload.
Author-email: Maxime Pires <maximepires4@gmail.com>
License: MIT
Project-URL: Homepage, https://github.com/maximepires4/epub-pipeline
Classifier: Development Status :: 3 - Alpha
Classifier: Intended Audience :: End Users/Desktop
Classifier: License :: OSI Approved :: MIT License
Classifier: Programming Language :: Python :: 3.12
Requires-Python: >=3.12
License-File: LICENSE
Requires-Dist: EbookLib>=0.18
Requires-Dist: requests>=2.28.0
Requires-Dist: Pillow>=9.0.0
Requires-Dist: python-dotenv>=1.0.0
Requires-Dist: google-api-python-client>=2.0.0
Requires-Dist: google-auth-httplib2>=0.1.0
Requires-Dist: google-auth-oauthlib>=1.0.0
Requires-Dist: termcolor
Provides-Extra: dev
Requires-Dist: pytest>=7.0; extra == "dev"
Requires-Dist: pytest-cov>=4.0; extra == "dev"
Requires-Dist: pytest-mock>=3.10; extra == "dev"
Requires-Dist: requests-mock>=1.11; extra == "dev"
Requires-Dist: ruff; extra == "dev"
Requires-Dist: mypy; extra == "dev"
Requires-Dist: types-requests; extra == "dev"
Requires-Dist: types-termcolor; extra == "dev"
Dynamic: license-file
